sopel_wikimedia/__init__.py
sopel_wikimedia/wikipedia/__init__.py
sopel_wikimedia/wikipedia/config.py
sopel_wikimedia/wikipedia/parser.py
sopel_wikimedia/wikipedia/plugin.py
sopel_wikimedia/wikipedia/wiki.py
sopel_wikimedia/wiktionary/__init__.py
sopel_wikimedia/wiktionary/impl.py
sopel_wikimedia/wiktionary/plugin.py
sopel_wikimedia-1.0.0.dist-info/licenses/LICENSE.txt
sopel_wikimedia-1.0.0.dist-info/METADATA
sopel_wikimedia-1.0.0.dist-info/WHEEL
sopel_wikimedia-1.0.0.dist-info/entry_points.txt
sopel_wikimedia-1.0.0.dist-info/top_level.txt
sopel_wikimedia-1.0.0.dist-info/RECORD
