Metadata-Version: 2.4
Name: sopel-wikimedia
Version: 1.0.0
Summary: Wikimedia plugin for Sopel
Author: Dimitri Molenaars
Author-email: Elad Alfassa <elad@fedoraproject.org>, dgw <dgw@technobabbl.es>, SnoopJ <snoopjedi@gmail.com>
Maintainer-email: dgw <dgw@technobabbl.es>, SnoopJ <snoopjedi@gmail.com>
License-Expression: EFL-2.0
Project-URL: Homepage, https://github.com/sopel-irc/sopel-wikimedia
Project-URL: Bug Tracker, https://github.com/sopel-irc/sopel-wikimedia/issues
Keywords: sopel,plugin,bot,irc
Platform: Linux x86, x86-64
Classifier: Development Status :: 5 - Production/Stable
Classifier: Intended Audience :: Developers
Classifier: Intended Audience :: System Administrators
Classifier: Operating System :: POSIX :: Linux
Classifier: Programming Language :: Python :: 3.8
Classifier: Programming Language :: Python :: 3.9
Classifier: Programming Language :: Python :: 3.10
Classifier: Programming Language :: Python :: 3.11
Classifier: Programming Language :: Python :: 3.12
Classifier: Programming Language :: Python :: 3.13
Classifier: Topic :: Communications :: Chat :: Internet Relay Chat
Requires-Python: <4,>=3.8
License-File: LICENSE.txt
Requires-Dist: sopel>=7.1
Dynamic: license-file
